discordnotifier/__init__.py
discord_notifier-0.0.3.dist-info/LICENSE
discord_notifier-0.0.3.dist-info/METADATA
discord_notifier-0.0.3.dist-info/WHEEL
discord_notifier-0.0.3.dist-info/entry_points.txt
discord_notifier-0.0.3.dist-info/top_level.txt
discord_notifier-0.0.3.dist-info/RECORD
